uplift_analysis/__init__.py
uplift_analysis/data.py
uplift_analysis/evaluation.py
uplift_analysis/scoring.py
uplift_analysis/utils.py
uplift_analysis/visualization.py
uplift_analysis-0.0.3.dist-info/AUTHORS.rst
uplift_analysis-0.0.3.dist-info/LICENSE
uplift_analysis-0.0.3.dist-info/METADATA
uplift_analysis-0.0.3.dist-info/WHEEL
uplift_analysis-0.0.3.dist-info/top_level.txt
uplift_analysis-0.0.3.dist-info/RECORD
